rtl/memory/basic_mem.sv



module basic_mem
//import system_config::*;
(
    // Global inputs
    input logic clk,
    input logic rst_n,
    input logic[xlen-1:0] adr,

    // Outputs
    output logic[xlen-1:0] resp_data
);
parameter xlen = 32;
parameter CELL_SIZE = 8;
parameter NB_CELLS = 1024;


logic [CELL_SIZE-1:0] data[NB_CELLS-1:0];




always @(posedge clk or negedge rst_n) begin
  if(rst_n) begin
    resp_data <= {data[adr+3], data[adr+2], data[adr+1], data[adr]};
  end
end

endmodule

rtl/ifetch.sv




module ifetch
//import CPU_config::*;
(
	// Global interface
	input logic clk,
	input logic rst_n,

	// Decode interface
	
	// Memory interface
  output logic[xlen-1:0] target_address
);
parameter xlen = 32;

logic[xlen-1:0] start_address = 'h0;



// Target address
initial begin
  target_address = start_address;
end

always @(posedge clk or negedge rst_n) begin
  if(rst_n)begin
    target_address <= target_address + 4;
  end
end

endmodule

rtl/cpu.sv



module cpu
//import CPU_config::*;
(
  // Global inputs
  input logic clk,
  input logic rst_n,

  
  // system inputs
  /* verilator lint_off UNUSED */
  input logic [xlen-1:0] resp_data,
  /* verilator lint_on UNUSED */
  // system outputs
  output logic [xlen-1:0] adr

);
  parameter xlen = 32;
  
  // instruction fetch Unit
  ifetch ifetch
  (
    .clk(clk),
    .rst_n(rst_n),
    .target_address(adr)
  );



endmodule

build/sim/tb_cpu.sv





module tb_cpu
//import system_config::*;
(
  input logic clk,
  input logic rst_n
);
  parameter xlen = 32;
  // Debug
  //logic [32:0] counter;


  logic [xlen-1:0] adr;
  logic [xlen-1:0] resp_data = 32'h0;
  // MODULES:

  // CPU
  cpu cpu 
  (
    clk,
    rst_n,
    resp_data,
    adr
  );

  // memory
  basic_mem mem
  (
    clk,
    rst_n,
    adr,
    resp_data
  );
  integer i;
  integer j;
  initial begin
    $display("Loading memory.");
    
    $readmemh("../../software/tests/ihex", mem.data);      
  end


endmodule

build/sim/waveform.vcd
$version Generated by VerilatedVcd $end
$date Sat May  6 22:11:59 2023
 $end
$timescale   1ps $end

 $scope module TOP $end
  $var wire  1 # clk $end
  $var wire  1 $ rst_n $end
  $scope module tb_cpu $end
   $var wire 32 % adr [31:0] $end
   $var wire  1 # clk $end
   $var wire 32 ( i [31:0] $end
   $var wire 32 ) j [31:0] $end
   $var wire 32 & resp_data [31:0] $end
   $var wire  1 $ rst_n $end
   $var wire 32 ' xlen [31:0] $end
   $scope module cpu $end
    $var wire 32 % adr [31:0] $end
    $var wire  1 # clk $end
    $var wire 32 & resp_data [31:0] $end
    $var wire  1 $ rst_n $end
    $var wire 32 ' xlen [31:0] $end
    $scope module ifetch $end
     $var wire  1 # clk $end
     $var wire  1 $ rst_n $end
     $var wire 32 * start_address [31:0] $end
     $var wire 32 % target_address [31:0] $end
     $var wire 32 ' xlen [31:0] $end
    $upscope $end
   $upscope $end
   $scope module mem $end
    $var wire 32 + CELL_SIZE [31:0] $end
    $var wire 32 , NB_CELLS [31:0] $end
    $var wire 32 % adr [31:0] $end
    $var wire  1 # clk $end
    $var wire 32 & resp_data [31:0] $end
    $var wire  1 $ rst_n $end
    $var wire 32 ' xlen [31:0] $end
   $upscope $end
  $upscope $end
 $upscope $end
$enddefinitions $end


#0
1#
0$
b00000000000000000000000000000000 %
b00000000000000000000000000000000 &
b00000000000000000000000000100000 '
b00000000000000000000000000000000 (
b00000000000000000000000000000000 )
b00000000000000000000000000000000 *
b00000000000000000000000000001000 +
b00000000000000000000010000000000 ,
#1
0#
#2
1#
#3
0#
#4
1#
#5
0#
#6
1#
#7
0#
#8
1#
#9
0#
#10
1#
#11
0#
#12
1#
#13
0#
#14
1#
#15
0#
#16
1#
#17
0#
#18
1#
#19
0#
#20
1#
#21
0#
#22
1#
#23
0#
#24
1#
#25
0#
#26
1#
#27
0#
#28
1#
#29
0#
#30
1#
#31
0#
#32
1#
#33
0#
#34
1#
#35
0#
#36
1#
#37
0#
#38
1#
#39
0#
#40
1#
#41
0#
#42
1#
#43
0#
#44
1#
#45
0#
#46
1#
#47
0#
#48
1#
#49
0#
#50
1#
#51
0#
#52
1#
#53
0#
#54
1#
#55
0#
#56
1#
#57
0#
#58
1#
#59
0#
#60
1#
#61
0#
#62
1#
#63
0#
#64
1#
#65
0#
#66
1#
#67
0#
#68
1#
#69
0#
#70
1#
#71
0#
#72
1#
#73
0#
#74
1#
#75
0#
#76
1#
#77
0#
#78
1#
#79
0#
#80
1#
#81
0#
#82
1#
#83
0#
#84
1#
#85
0#
#86
1#
#87
0#
#88
1#
#89
0#
#90
1#
#91
0#
#92
1#
#93
0#
#94
1#
#95
0#
#96
1#
#97
0#
#98
1#
#99
0#
#100
1#
1$
b00000000000000000000000000000100 %
b11111110000000010000000100010011 &
#101
0#
#102
1#
b00000000000000000000000000001000 %
b00000000100000010010111000100011 &
#103
0#
#104
1#
b00000000000000000000000000001100 %
b00000010000000010000010000010011 &
#105
0#
#106
1#
b00000000000000000000000000010000 %
b00000000000100000000011110010011 &
#107
0#
#108
1#
b00000000000000000000000000010100 %
b11111110111101000010011000100011 &
#109
0#
#110
1#
b00000000000000000000000000011000 %
b00000000001000000000011110010011 &
#111
0#
#112
1#
b00000000000000000000000000011100 %
b11111110111101000010010000100011 &
#113
0#
#114
1#
b00000000000000000000000000100000 %
b11111110110001000010011100000011 &
#115
0#
#116
1#
b00000000000000000000000000100100 %
b11111110100001000010011110000011 &
#117
0#
#118
1#
b00000000000000000000000000101000 %
b00000000111101110000011110110011 &
#119
0#
#120
1#
b00000000000000000000000000101100 %
b11111110111101000010001000100011 &
#121
0#
#122
1#
b00000000000000000000000000110000 %
b11111110010001000010011110000011 &
#123
0#
#124
1#
b00000000000000000000000000110100 %
b11111111110101111000011110010011 &
#125
0#
#126
1#
b00000000000000000000000000111000 %
b00000000000101111011011110010011 &
#127
0#
#128
1#
b00000000000000000000000000111100 %
b00001111111101111111011110010011 &
#129
0#
#130
1#
b00000000000000000000000001000000 %
b00000000000001111000010100010011 &
#131
0#
#132
1#
b00000000000000000000000001000100 %
b00000001110000010010010000000011 &
#133
0#
#134
1#
b00000000000000000000000001001000 %
b00000010000000010000000100010011 &
#135
0#
#136
1#
b00000000000000000000000001001100 %
b00000000000000001000000001100111 &
#137
0#
#138
1#
b00000000000000000000000001010000 %
b00000000000000000000000000000000 &
#139
0#
#140
1#
b00000000000000000000000001010100 %
#141
0#
#142
1#
b00000000000000000000000001011000 %
#143
0#
#144
1#
b00000000000000000000000001011100 %
#145
0#
#146
1#
b00000000000000000000000001100000 %
#147
0#
#148
1#
b00000000000000000000000001100100 %
#149
0#
#150
1#
b00000000000000000000000001101000 %
#151
0#
#152
1#
b00000000000000000000000001101100 %
#153
0#
#154
1#
b00000000000000000000000001110000 %
#155
0#
#156
1#
b00000000000000000000000001110100 %
#157
0#
#158
1#
b00000000000000000000000001111000 %
#159
0#
#160
1#
b00000000000000000000000001111100 %
#161
0#
#162
1#
b00000000000000000000000010000000 %
#163
0#
#164
1#
b00000000000000000000000010000100 %
#165
0#
#166
1#
b00000000000000000000000010001000 %
#167
0#
#168
1#
b00000000000000000000000010001100 %
#169
0#
#170
1#
b00000000000000000000000010010000 %
#171
0#
#172
1#
b00000000000000000000000010010100 %
#173
0#
#174
1#
b00000000000000000000000010011000 %
#175
0#
#176
1#
b00000000000000000000000010011100 %
#177
0#
#178
1#
b00000000000000000000000010100000 %
#179
0#
#180
1#
b00000000000000000000000010100100 %
#181
0#
#182
1#
b00000000000000000000000010101000 %
#183
0#
#184
1#
b00000000000000000000000010101100 %
#185
0#
#186
1#
b00000000000000000000000010110000 %
#187
0#
#188
1#
b00000000000000000000000010110100 %
#189
0#
#190
1#
b00000000000000000000000010111000 %
#191
0#
#192
1#
b00000000000000000000000010111100 %
#193
0#
#194
1#
b00000000000000000000000011000000 %
#195
0#
#196
1#
b00000000000000000000000011000100 %
#197
0#
#198
1#
b00000000000000000000000011001000 %
#199
0#
#200
1#
b00000000000000000000000011001100 %
#201
0#
#202
1#
b00000000000000000000000011010000 %
#203
0#
#204
1#
b00000000000000000000000011010100 %
#205
0#
#206
1#
b00000000000000000000000011011000 %
#207
0#
#208
1#
b00000000000000000000000011011100 %
#209
0#
#210
1#
b00000000000000000000000011100000 %
#211
0#
#212
1#
b00000000000000000000000011100100 %
#213
0#
#214
1#
b00000000000000000000000011101000 %
#215
0#
#216
1#
b00000000000000000000000011101100 %
#217
0#
#218
1#
b00000000000000000000000011110000 %
#219
0#
#220
1#
b00000000000000000000000011110100 %
#221
0#
#222
1#
b00000000000000000000000011111000 %
#223
0#
#224
1#
b00000000000000000000000011111100 %
#225
0#
#226
1#
b00000000000000000000000100000000 %
#227
0#
#228
1#
b00000000000000000000000100000100 %
#229
0#
#230
1#
b00000000000000000000000100001000 %
#231
0#
#232
1#
b00000000000000000000000100001100 %
#233
0#
#234
1#
b00000000000000000000000100010000 %
#235
0#
#236
1#
b00000000000000000000000100010100 %
#237
0#
#238
1#
b00000000000000000000000100011000 %
#239
0#
#240
1#
b00000000000000000000000100011100 %
#241
0#
#242
1#
b00000000000000000000000100100000 %
#243
0#
#244
1#
b00000000000000000000000100100100 %
#245
0#
#246
1#
b00000000000000000000000100101000 %
#247
0#
#248
1#
b00000000000000000000000100101100 %
#249
0#
#250
1#
b00000000000000000000000100110000 %
#251
0#
#252
1#
b00000000000000000000000100110100 %
#253
0#
#254
1#
b00000000000000000000000100111000 %
#255
0#
#256
1#
b00000000000000000000000100111100 %
#257
0#
#258
1#
b00000000000000000000000101000000 %
#259
0#
#260
1#
b00000000000000000000000101000100 %
#261
0#
#262
1#
b00000000000000000000000101001000 %
#263
0#
#264
1#
b00000000000000000000000101001100 %
#265
0#
#266
1#
b00000000000000000000000101010000 %
#267
0#
#268
1#
b00000000000000000000000101010100 %
#269
0#
#270
1#
b00000000000000000000000101011000 %
#271
0#
#272
1#
b00000000000000000000000101011100 %
#273
0#
#274
1#
b00000000000000000000000101100000 %
#275
0#
#276
1#
b00000000000000000000000101100100 %
#277
0#
#278
1#
b00000000000000000000000101101000 %
#279
0#
#280
1#
b00000000000000000000000101101100 %
#281
0#
#282
1#
b00000000000000000000000101110000 %
#283
0#
#284
1#
b00000000000000000000000101110100 %
#285
0#
#286
1#
b00000000000000000000000101111000 %
#287
0#
#288
1#
b00000000000000000000000101111100 %
#289
0#
#290
1#
b00000000000000000000000110000000 %
#291
0#
#292
1#
b00000000000000000000000110000100 %
#293
0#
#294
1#
b00000000000000000000000110001000 %
#295
0#
#296
1#
b00000000000000000000000110001100 %
#297
0#
#298
1#
b00000000000000000000000110010000 %
#299
0#
#300
1#
b00000000000000000000000110010100 %
#301
0#
#302
1#
b00000000000000000000000110011000 %
#303
0#
#304
1#
b00000000000000000000000110011100 %
#305
0#
#306
1#
b00000000000000000000000110100000 %
#307
0#
#308
1#
b00000000000000000000000110100100 %
#309
0#
#310
1#
b00000000000000000000000110101000 %
#311
0#
#312
1#
b00000000000000000000000110101100 %
#313
0#
#314
1#
b00000000000000000000000110110000 %
#315
0#
#316
1#
b00000000000000000000000110110100 %
#317
0#
#318
1#
b00000000000000000000000110111000 %
#319
0#
#320
1#
b00000000000000000000000110111100 %
#321
0#
#322
1#
b00000000000000000000000111000000 %
#323
0#
#324
1#
b00000000000000000000000111000100 %
#325
0#
#326
1#
b00000000000000000000000111001000 %
#327
0#
#328
1#
b00000000000000000000000111001100 %
#329
0#
#330
1#
b00000000000000000000000111010000 %
#331
0#
#332
1#
b00000000000000000000000111010100 %
#333
0#
#334
1#
b00000000000000000000000111011000 %
#335
0#
#336
1#
b00000000000000000000000111011100 %
#337
0#
#338
1#
b00000000000000000000000111100000 %
#339
0#
#340
1#
b00000000000000000000000111100100 %
#341
0#
#342
1#
b00000000000000000000000111101000 %
#343
0#
#344
1#
b00000000000000000000000111101100 %
#345
0#
#346
1#
b00000000000000000000000111110000 %
#347
0#
#348
1#
b00000000000000000000000111110100 %
#349
0#
#350
1#
b00000000000000000000000111111000 %
#351
0#
#352
1#
b00000000000000000000000111111100 %
#353
0#
#354
1#
b00000000000000000000001000000000 %
#355
0#
#356
1#
b00000000000000000000001000000100 %
#357
0#
#358
1#
b00000000000000000000001000001000 %
#359
0#
#360
1#
b00000000000000000000001000001100 %
#361
0#
#362
1#
b00000000000000000000001000010000 %
#363
0#
#364
1#
b00000000000000000000001000010100 %
#365
0#
#366
1#
b00000000000000000000001000011000 %
#367
0#
#368
1#
b00000000000000000000001000011100 %
#369
0#
#370
1#
b00000000000000000000001000100000 %
#371
0#
#372
1#
b00000000000000000000001000100100 %
#373
0#
#374
1#
b00000000000000000000001000101000 %
#375
0#
#376
1#
b00000000000000000000001000101100 %
#377
0#
#378
1#
b00000000000000000000001000110000 %
#379
0#
#380
1#
b00000000000000000000001000110100 %
#381
0#
#382
1#
b00000000000000000000001000111000 %
#383
0#
#384
1#
b00000000000000000000001000111100 %
#385
0#
#386
1#
b00000000000000000000001001000000 %
#387
0#
#388
1#
b00000000000000000000001001000100 %
#389
0#
#390
1#
b00000000000000000000001001001000 %
#391
0#
#392
1#
b00000000000000000000001001001100 %
#393
0#
#394
1#
b00000000000000000000001001010000 %
#395
0#
#396
1#
b00000000000000000000001001010100 %
#397
0#
#398
1#
b00000000000000000000001001011000 %
#399
0#
#400
1#
b00000000000000000000001001011100 %
#401
0#
#402
1#
b00000000000000000000001001100000 %
#403
0#
#404
1#
b00000000000000000000001001100100 %
#405
0#
#406
1#
b00000000000000000000001001101000 %
#407
0#
#408
1#
b00000000000000000000001001101100 %
#409
0#
#410
1#
b00000000000000000000001001110000 %
#411
0#
#412
1#
b00000000000000000000001001110100 %
#413
0#
#414
1#
b00000000000000000000001001111000 %
#415
0#
#416
1#
b00000000000000000000001001111100 %
#417
0#
#418
1#
b00000000000000000000001010000000 %
#419
0#
#420
1#
b00000000000000000000001010000100 %
#421
0#
#422
1#
b00000000000000000000001010001000 %
#423
0#
#424
1#
b00000000000000000000001010001100 %
#425
0#
#426
1#
b00000000000000000000001010010000 %
#427
0#
#428
1#
b00000000000000000000001010010100 %
#429
0#
#430
1#
b00000000000000000000001010011000 %
#431
0#
#432
1#
b00000000000000000000001010011100 %
#433
0#
#434
1#
b00000000000000000000001010100000 %
#435
0#
#436
1#
b00000000000000000000001010100100 %
#437
0#
#438
1#
b00000000000000000000001010101000 %
#439
0#
#440
1#
b00000000000000000000001010101100 %
#441
0#
#442
1#
b00000000000000000000001010110000 %
#443
0#
#444
1#
b00000000000000000000001010110100 %
#445
0#
#446
1#
b00000000000000000000001010111000 %
#447
0#
#448
1#
b00000000000000000000001010111100 %
#449
0#
#450
1#
b00000000000000000000001011000000 %
#451
0#
#452
1#
b00000000000000000000001011000100 %
#453
0#
#454
1#
b00000000000000000000001011001000 %
#455
0#
#456
1#
b00000000000000000000001011001100 %
#457
0#
#458
1#
b00000000000000000000001011010000 %
#459
0#
#460
1#
b00000000000000000000001011010100 %
#461
0#
#462
1#
b00000000000000000000001011011000 %
#463
0#
#464
1#
b00000000000000000000001011011100 %
#465
0#
#466
1#
b00000000000000000000001011100000 %
#467
0#
#468
1#
b00000000000000000000001011100100 %
#469
0#
#470
1#
b00000000000000000000001011101000 %
#471
0#
#472
1#
b00000000000000000000001011101100 %
#473
0#
#474
1#
b00000000000000000000001011110000 %
#475
0#
#476
1#
b00000000000000000000001011110100 %
#477
0#
#478
1#
b00000000000000000000001011111000 %
#479
0#
#480
1#
b00000000000000000000001011111100 %
#481
0#
#482
1#
b00000000000000000000001100000000 %
#483
0#
#484
1#
b00000000000000000000001100000100 %
#485
0#
#486
1#
b00000000000000000000001100001000 %
#487
0#
#488
1#
b00000000000000000000001100001100 %
#489
0#
#490
1#
b00000000000000000000001100010000 %
#491
0#
#492
1#
b00000000000000000000001100010100 %
#493
0#
#494
1#
b00000000000000000000001100011000 %
#495
0#
#496
1#
b00000000000000000000001100011100 %
#497
0#
#498
1#
b00000000000000000000001100100000 %
#499
0#
#500
1#
b00000000000000000000001100100100 %
#501
0#
#502
1#
b00000000000000000000001100101000 %
#503
0#
#504
1#
b00000000000000000000001100101100 %
#505
0#
#506
1#
b00000000000000000000001100110000 %
#507
0#
#508
1#
b00000000000000000000001100110100 %
#509
0#
#510
1#
b00000000000000000000001100111000 %
#511
0#
#512
1#
b00000000000000000000001100111100 %
#513
0#
#514
1#
b00000000000000000000001101000000 %
#515
0#
#516
1#
b00000000000000000000001101000100 %
#517
0#
#518
1#
b00000000000000000000001101001000 %
#519
0#
#520
1#
b00000000000000000000001101001100 %
#521
0#
#522
1#
b00000000000000000000001101010000 %
#523
0#
#524
1#
b00000000000000000000001101010100 %
#525
0#
#526
1#
b00000000000000000000001101011000 %
#527
0#
#528
1#
b00000000000000000000001101011100 %
#529
0#
#530
1#
b00000000000000000000001101100000 %
#531
0#
#532
1#
b00000000000000000000001101100100 %
#533
0#
#534
1#
b00000000000000000000001101101000 %
#535
0#
#536
1#
b00000000000000000000001101101100 %
#537
0#
#538
1#
b00000000000000000000001101110000 %
#539
0#
#540
1#
b00000000000000000000001101110100 %
#541
0#
#542
1#
b00000000000000000000001101111000 %
#543
0#
#544
1#
b00000000000000000000001101111100 %
#545
0#
#546
1#
b00000000000000000000001110000000 %
#547
0#
#548
1#
b00000000000000000000001110000100 %
#549
0#
#550
1#
b00000000000000000000001110001000 %
#551
0#
#552
1#
b00000000000000000000001110001100 %
#553
0#
#554
1#
b00000000000000000000001110010000 %
#555
0#
#556
1#
b00000000000000000000001110010100 %
#557
0#
#558
1#
b00000000000000000000001110011000 %
#559
0#
#560
1#
b00000000000000000000001110011100 %
#561
0#
#562
1#
b00000000000000000000001110100000 %
#563
0#
#564
1#
b00000000000000000000001110100100 %
#565
0#
#566
1#
b00000000000000000000001110101000 %
#567
0#
#568
1#
b00000000000000000000001110101100 %
#569
0#
#570
1#
b00000000000000000000001110110000 %
#571
0#
#572
1#
b00000000000000000000001110110100 %
#573
0#
#574
1#
b00000000000000000000001110111000 %
#575
0#
#576
1#
b00000000000000000000001110111100 %
#577
0#
#578
1#
b00000000000000000000001111000000 %
#579
0#
#580
1#
b00000000000000000000001111000100 %
#581
0#
#582
1#
b00000000000000000000001111001000 %
#583
0#
#584
1#
b00000000000000000000001111001100 %
#585
0#
#586
1#
b00000000000000000000001111010000 %
#587
0#
#588
1#
b00000000000000000000001111010100 %
#589
0#
#590
1#
b00000000000000000000001111011000 %
#591
0#
#592
1#
b00000000000000000000001111011100 %
#593
0#
#594
1#
b00000000000000000000001111100000 %
#595
0#
#596
1#
b00000000000000000000001111100100 %
#597
0#
#598
1#
b00000000000000000000001111101000 %
#599
0#
#600
1#
b00000000000000000000001111101100 %
#601
0#
#602
1#
b00000000000000000000001111110000 %
#603
0#
#604
1#
b00000000000000000000001111110100 %
#605
0#
#606
1#
b00000000000000000000001111111000 %
#607
0#
#608
1#
b00000000000000000000001111111100 %
#609
0#
#610
1#
b00000000000000000000010000000000 %
#611
0#
#612
1#
b00000000000000000000010000000100 %
b11111110000000010000000100010011 &
#613
0#
#614
1#
b00000000000000000000010000001000 %
b00000000100000010010111000100011 &
#615
0#
#616
1#
b00000000000000000000010000001100 %
b00000010000000010000010000010011 &
#617
0#
#618
1#
b00000000000000000000010000010000 %
b00000000000100000000011110010011 &
#619
0#
#620
1#
b00000000000000000000010000010100 %
b11111110111101000010011000100011 &
#621
0#
#622
1#
b00000000000000000000010000011000 %
b00000000001000000000011110010011 &
#623
0#
#624
1#
b00000000000000000000010000011100 %
b11111110111101000010010000100011 &
#625
0#
#626
1#
b00000000000000000000010000100000 %
b11111110110001000010011100000011 &
#627
0#
#628
1#
b00000000000000000000010000100100 %
b11111110100001000010011110000011 &
#629
0#
#630
1#
b00000000000000000000010000101000 %
b00000000111101110000011110110011 &
#631
0#
#632
1#
b00000000000000000000010000101100 %
b11111110111101000010001000100011 &
#633
0#
#634
1#
b00000000000000000000010000110000 %
b11111110010001000010011110000011 &
#635
0#
#636
1#
b00000000000000000000010000110100 %
b11111111110101111000011110010011 &
#637
0#
#638
1#
b00000000000000000000010000111000 %
b00000000000101111011011110010011 &
#639
0#
#640
1#
b00000000000000000000010000111100 %
b00001111111101111111011110010011 &
#641
0#
#642
1#
b00000000000000000000010001000000 %
b00000000000001111000010100010011 &
#643
0#
#644
1#
b00000000000000000000010001000100 %
b00000001110000010010010000000011 &
#645
0#
#646
1#
b00000000000000000000010001001000 %
b00000010000000010000000100010011 &
#647
0#
#648
1#
b00000000000000000000010001001100 %
b00000000000000001000000001100111 &
#649
0#
#650
1#
b00000000000000000000010001010000 %
b00000000000000000000000000000000 &
#651
0#
#652
1#
b00000000000000000000010001010100 %
#653
0#
#654
1#
b00000000000000000000010001011000 %
#655
0#
#656
1#
b00000000000000000000010001011100 %
#657
0#
#658
1#
b00000000000000000000010001100000 %
#659
0#
#660
1#
b00000000000000000000010001100100 %
#661
0#
#662
1#
b00000000000000000000010001101000 %
#663
0#
#664
1#
b00000000000000000000010001101100 %
#665
0#
#666
1#
b00000000000000000000010001110000 %
#667
0#
#668
1#
b00000000000000000000010001110100 %
#669
0#
#670
1#
b00000000000000000000010001111000 %
#671
0#
#672
1#
b00000000000000000000010001111100 %
#673
0#
#674
1#
b00000000000000000000010010000000 %
#675
0#
#676
1#
b00000000000000000000010010000100 %
#677
0#
#678
1#
b00000000000000000000010010001000 %
#679
0#
#680
1#
b00000000000000000000010010001100 %
#681
0#
#682
1#
b00000000000000000000010010010000 %
#683
0#
#684
1#
b00000000000000000000010010010100 %
#685
0#
#686
1#
b00000000000000000000010010011000 %
#687
0#
#688
1#
b00000000000000000000010010011100 %
#689
0#
#690
1#
b00000000000000000000010010100000 %
#691
0#
#692
1#
b00000000000000000000010010100100 %
#693
0#
#694
1#
b00000000000000000000010010101000 %
#695
0#
#696
1#
b00000000000000000000010010101100 %
#697
0#
#698
1#
b00000000000000000000010010110000 %
#699
0#
#700
1#
b00000000000000000000010010110100 %
#701
0#
#702
1#
b00000000000000000000010010111000 %
#703
0#
#704
1#
b00000000000000000000010010111100 %
#705
0#
#706
1#
b00000000000000000000010011000000 %
#707
0#
#708
1#
b00000000000000000000010011000100 %
#709
0#
#710
1#
b00000000000000000000010011001000 %
#711
0#
#712
1#
b00000000000000000000010011001100 %
#713
0#
#714
1#
b00000000000000000000010011010000 %
#715
0#
#716
1#
b00000000000000000000010011010100 %
#717
0#
#718
1#
b00000000000000000000010011011000 %
#719
0#
#720
1#
b00000000000000000000010011011100 %
#721
0#
#722
1#
b00000000000000000000010011100000 %
#723
0#
#724
1#
b00000000000000000000010011100100 %
#725
0#
#726
1#
b00000000000000000000010011101000 %
#727
0#
#728
1#
b00000000000000000000010011101100 %
#729
0#
#730
1#
b00000000000000000000010011110000 %
#731
0#
#732
1#
b00000000000000000000010011110100 %
#733
0#
#734
1#
b00000000000000000000010011111000 %
#735
0#
#736
1#
b00000000000000000000010011111100 %
#737
0#
#738
1#
b00000000000000000000010100000000 %
#739
0#
#740
1#
b00000000000000000000010100000100 %
#741
0#
#742
1#
b00000000000000000000010100001000 %
#743
0#
#744
1#
b00000000000000000000010100001100 %
#745
0#
#746
1#
b00000000000000000000010100010000 %
#747
0#
#748
1#
b00000000000000000000010100010100 %
#749
0#
#750
1#
b00000000000000000000010100011000 %
#751
0#
#752
1#
b00000000000000000000010100011100 %
#753
0#
#754
1#
b00000000000000000000010100100000 %
#755
0#
#756
1#
b00000000000000000000010100100100 %
#757
0#
#758
1#
b00000000000000000000010100101000 %
#759
0#
#760
1#
b00000000000000000000010100101100 %
#761
0#
#762
1#
b00000000000000000000010100110000 %
#763
0#
#764
1#
b00000000000000000000010100110100 %
#765
0#
#766
1#
b00000000000000000000010100111000 %
#767
0#
#768
1#
b00000000000000000000010100111100 %
#769
0#
#770
1#
b00000000000000000000010101000000 %
#771
0#
#772
1#
b00000000000000000000010101000100 %
#773
0#
#774
1#
b00000000000000000000010101001000 %
#775
0#
#776
1#
b00000000000000000000010101001100 %
#777
0#
#778
1#
b00000000000000000000010101010000 %
#779
0#
#780
1#
b00000000000000000000010101010100 %
#781
0#
#782
1#
b00000000000000000000010101011000 %
#783
0#
#784
1#
b00000000000000000000010101011100 %
#785
0#
#786
1#
b00000000000000000000010101100000 %
#787
0#
#788
1#
b00000000000000000000010101100100 %
#789
0#
#790
1#
b00000000000000000000010101101000 %
#791
0#
#792
1#
b00000000000000000000010101101100 %
#793
0#
#794
1#
b00000000000000000000010101110000 %
#795
0#
#796
1#
b00000000000000000000010101110100 %
#797
0#
#798
1#
b00000000000000000000010101111000 %
#799
0#
#800
1#
b00000000000000000000010101111100 %
#801
0#
#802
1#
b00000000000000000000010110000000 %
#803
0#
#804
1#
b00000000000000000000010110000100 %
#805
0#
#806
1#
b00000000000000000000010110001000 %
#807
0#
#808
1#
b00000000000000000000010110001100 %
#809
0#
#810
1#
b00000000000000000000010110010000 %
#811
0#
#812
1#
b00000000000000000000010110010100 %
#813
0#
#814
1#
b00000000000000000000010110011000 %
#815
0#
#816
1#
b00000000000000000000010110011100 %
#817
0#
#818
1#
b00000000000000000000010110100000 %
#819
0#
#820
1#
b00000000000000000000010110100100 %
#821
0#
#822
1#
b00000000000000000000010110101000 %
#823
0#
#824
1#
b00000000000000000000010110101100 %
#825
0#
#826
1#
b00000000000000000000010110110000 %
#827
0#
#828
1#
b00000000000000000000010110110100 %
#829
0#
#830
1#
b00000000000000000000010110111000 %
#831
0#
#832
1#
b00000000000000000000010110111100 %
#833
0#
#834
1#
b00000000000000000000010111000000 %
#835
0#
#836
1#
b00000000000000000000010111000100 %
#837
0#
#838
1#
b00000000000000000000010111001000 %
#839
0#
#840
1#
b00000000000000000000010111001100 %
#841
0#
#842
1#
b00000000000000000000010111010000 %
#843
0#
#844
1#
b00000000000000000000010111010100 %
#845
0#
#846
1#
b00000000000000000000010111011000 %
#847
0#
#848
1#
b00000000000000000000010111011100 %
#849
0#
#850
1#
b00000000000000000000010111100000 %
#851
0#
#852
1#
b00000000000000000000010111100100 %
#853
0#
#854
1#
b00000000000000000000010111101000 %
#855
0#
#856
1#
b00000000000000000000010111101100 %
#857
0#
#858
1#
b00000000000000000000010111110000 %
#859
0#
#860
1#
b00000000000000000000010111110100 %
#861
0#
#862
1#
b00000000000000000000010111111000 %
#863
0#
#864
1#
b00000000000000000000010111111100 %
#865
0#
#866
1#
b00000000000000000000011000000000 %
#867
0#
#868
1#
b00000000000000000000011000000100 %
#869
0#
#870
1#
b00000000000000000000011000001000 %
#871
0#
#872
1#
b00000000000000000000011000001100 %
#873
0#
#874
1#
b00000000000000000000011000010000 %
#875
0#
#876
1#
b00000000000000000000011000010100 %
#877
0#
#878
1#
b00000000000000000000011000011000 %
#879
0#
#880
1#
b00000000000000000000011000011100 %
#881
0#
#882
1#
b00000000000000000000011000100000 %
#883
0#
#884
1#
b00000000000000000000011000100100 %
#885
0#
#886
1#
b00000000000000000000011000101000 %
#887
0#
#888
1#
b00000000000000000000011000101100 %
#889
0#
#890
1#
b00000000000000000000011000110000 %
#891
0#
#892
1#
b00000000000000000000011000110100 %
#893
0#
#894
1#
b00000000000000000000011000111000 %
#895
0#
#896
1#
b00000000000000000000011000111100 %
#897
0#
#898
1#
b00000000000000000000011001000000 %
#899
0#
#900
1#
b00000000000000000000011001000100 %
#901
0#
#902
1#
b00000000000000000000011001001000 %
#903
0#
#904
1#
b00000000000000000000011001001100 %
#905
0#
#906
1#
b00000000000000000000011001010000 %
#907
0#
#908
1#
b00000000000000000000011001010100 %
#909
0#
#910
1#
b00000000000000000000011001011000 %
#911
0#
#912
1#
b00000000000000000000011001011100 %
#913
0#
#914
1#
b00000000000000000000011001100000 %
#915
0#
#916
1#
b00000000000000000000011001100100 %
#917
0#
#918
1#
b00000000000000000000011001101000 %
#919
0#
#920
1#
b00000000000000000000011001101100 %
#921
0#
#922
1#
b00000000000000000000011001110000 %
#923
0#
#924
1#
b00000000000000000000011001110100 %
#925
0#
#926
1#
b00000000000000000000011001111000 %
#927
0#
#928
1#
b00000000000000000000011001111100 %
#929
0#
#930
1#
b00000000000000000000011010000000 %
#931
0#
#932
1#
b00000000000000000000011010000100 %
#933
0#
#934
1#
b00000000000000000000011010001000 %
#935
0#
#936
1#
b00000000000000000000011010001100 %
#937
0#
#938
1#
b00000000000000000000011010010000 %
#939
0#
#940
1#
b00000000000000000000011010010100 %
#941
0#
#942
1#
b00000000000000000000011010011000 %
#943
0#
#944
1#
b00000000000000000000011010011100 %
#945
0#
#946
1#
b00000000000000000000011010100000 %
#947
0#
#948
1#
b00000000000000000000011010100100 %
#949
0#
#950
1#
b00000000000000000000011010101000 %
#951
0#
#952
1#
b00000000000000000000011010101100 %
#953
0#
#954
1#
b00000000000000000000011010110000 %
#955
0#
#956
1#
b00000000000000000000011010110100 %
#957
0#
#958
1#
b00000000000000000000011010111000 %
#959
0#
#960
1#
b00000000000000000000011010111100 %
#961
0#
#962
1#
b00000000000000000000011011000000 %
#963
0#
#964
1#
b00000000000000000000011011000100 %
#965
0#
#966
1#
b00000000000000000000011011001000 %
#967
0#
#968
1#
b00000000000000000000011011001100 %
#969
0#
#970
1#
b00000000000000000000011011010000 %
#971
0#
#972
1#
b00000000000000000000011011010100 %
#973
0#
#974
1#
b00000000000000000000011011011000 %
#975
0#
#976
1#
b00000000000000000000011011011100 %
#977
0#
#978
1#
b00000000000000000000011011100000 %
#979
0#
#980
1#
b00000000000000000000011011100100 %
#981
0#
#982
1#
b00000000000000000000011011101000 %
#983
0#
#984
1#
b00000000000000000000011011101100 %
#985
0#
#986
1#
b00000000000000000000011011110000 %
#987
0#
#988
1#
b00000000000000000000011011110100 %
#989
0#
#990
1#
b00000000000000000000011011111000 %
#991
0#
