rtl/memory/basic_mem.sv



module basic_mem
//import system_config::*;
(
    // Global inputs
    input logic clk,
    input logic rst_n,
    input logic[xlen-1:0] adr,

    // Outputs
    output logic[xlen-1:0] resp_data
);
parameter xlen = 32;
parameter CELL_SIZE = 8;
parameter NB_CELLS = 1024;


logic [CELL_SIZE-1:0] data[NB_CELLS-1:0];




always @(negedge clk) begin
  if(rst_n) begin
    resp_data <= {data[adr+3], data[adr+2], data[adr+1], data[adr]};
  end
end

endmodule

rtl/cpu/register_manager.sv




module register_manager
(
  // Global interface
  input logic clk,
  input logic rst_n,

  // pc_gen interface
  input logic[32:0] data,
  output logic ok_o
  
  // calculations units interface
  
);




always begin
  ok_o = 1;
end


endmodule

rtl/utils/fifo.sv




module fifo 
#(parameter DATA_SIZE = 32)
(
  // Global interace
  input logic clk,
  input logic rst_n,

  // input
  input logic[DATA_SIZE-1:0] data_i,
  input logic valide,

  // output
  output logic[DATA_SIZE-1:0] data_o,
  input logic ok
);


// local variables
logic[DATA_SIZE-1:0] data;

// 

always @(posedge clk) begin
  if(rst_n && ok) begin
    data_o <= data;
  end
end

always begin
  if(valide) begin
    data = data_i;
  end
end

endmodule

rtl/cpu/decoder_PG.sv




module decoder_PG
(
  input logic[17:0] instruction,
  output logic[7:0] decode
);
parameter xlen = 32;

logic[3:0] instr_type;
logic[3:0] instr_code;

always  begin
  casez (instruction)
    18'b???????????0110111: // LUI
    begin
      instr_type = 'h5;
      instr_code = 'h0;
    end
    18'b???????????0010111: // AUIPC
    begin
      instr_type = 'h5;
      instr_code = 'h1;
    end
    18'b???????????1101111: // JAL
    begin
      instr_type = 'h6;
      instr_code = 'h0;
    end
    18'b????????0001100111: // JALR
    begin
      instr_type = 'h2;
      instr_code = 'h0;
    end
    18'b????????0001100011: // BEQ
    begin
      instr_type = 'h4;
      instr_code = 'h0;
    end
    18'b????????0011100011: // BNE
    begin
      instr_type = 'h4;
      instr_code = 'h1;
    end
    18'b????????1001100011: // BLT
    begin
      instr_type = 'h4;
      instr_code = 'h2;
    end
    18'b????????1011100011: // BGE
    begin
      instr_type = 'h4;
      instr_code = 'h3;
    end
    18'b????????1101100011: // BLTU
    begin
      instr_type = 'h4;
      instr_code = 'h4;
    end
    18'b????????1111100011: // BGEU
    begin
      instr_type = 'h4;
      instr_code = 'h5;
    end
    18'b????????0000000011: // LB
    begin
      instr_type = 'h2;
      instr_code = 'h1;
    end
    18'b????????0010000011: // LH
    begin
      instr_type = 'h2;
      instr_code = 'h2;
    end
    18'b????????0100000011: // LW
    begin
      instr_type = 'h2;
      instr_code = 'h3;
    end
    18'b????????1000000011: // LBU
    begin
      instr_type = 'h2;
      instr_code = 'h4;
    end
    18'b????????1010000011: // LHU 
    begin
      instr_type = 'h2;
      instr_code = 'h5;
    end
    18'b????????0000100011: // SB 
    begin
      instr_type = 'h3;
      instr_code = 'h0;
    end
    18'b????????0010100011: // SH 
    begin
      instr_type = 'h3;
      instr_code = 'h1;
    end
    18'b????????0100100011: // SW   
    begin
      instr_type = 'h3;
      instr_code = 'h2;
    end
    18'b????????0000010011: // ADDI 
    begin
      instr_type = 'h2;
      instr_code = 'h5;
    end
    18'b????????0100010011: // SLTI 
    begin
      instr_type = 'h2;
      instr_code = 'h6;
    end
    18'b????????0110010011: // SLTIU 
    begin
      instr_type = 'h2;
      instr_code = 'h7;
    end
    18'b????????1000010011: // XORI 
    begin
      instr_type = 'h2;
      instr_code = 'h8;
    end
    18'b????????1100010011: // ORI   
    begin
      instr_type = 'h2;
      instr_code = 'h9;
    end
    18'b????????1110010011: // ANDI 
    begin
      instr_type = 'h2;
      instr_code = 'ha;
    end
    18'b0000000?0010010011: // SLLI
    begin
      instr_type = 'h1;
      instr_code = 'h0;
    end
    18'b0000000?1010010011: // SRLI
    begin
      instr_type = 'h1;
      instr_code = 'h1;
    end
    18'b0100000?1010010011: // SRAI
    begin
      instr_type = 'h1;
      instr_code = 'h2;
    end
    18'b0000000?0000110011: // ADD
    begin
      instr_type = 'h1;
      instr_code = 'h3;
    end
    18'b0100000?0000110011: // SUB
    begin
      instr_type = 'h1;
      instr_code = 'h4;
    end
    18'b0000000?0010110011: // SLL
    begin
      instr_type = 'h1;
      instr_code = 'h5;
    end
    18'b0000000?0100110011: // SLT
    begin
      instr_type = 'h1;
      instr_code = 'h6;
    end
    18'b0000000?0110110011: // SLTU
    begin
      instr_type = 'h1;
      instr_code = 'h7;
    end
    18'b0000000?1000110011: // XOR
    begin
      instr_type = 'h1;
      instr_code = 'h8;
    end
    18'b0000000?1010110011: // SRL
    begin
      instr_type = 'h1;
      instr_code = 'h9;
    end
    18'b0100000?1010110011: // SRA
    begin
      instr_type = 'h1;
      instr_code = 'ha;
    end
    18'b0000000?1100110011: // OR
    begin
      instr_type = 'h1;
      instr_code = 'hb;
    end
    18'b0000000?1110110011: // AND
    begin
      instr_type = 'h1;
      instr_code = 'hc;
    end
    18'b0000????0000001111: // FENCE
    begin
      instr_type = 'h7;
      instr_code = 'h0;
    end
    18'b000000000010001111: // FENCE.I
    begin
      instr_type = 'h7;
      instr_code = 'h1;
    end
    18'b000000000001110011: // ECALL
    begin
      instr_type = 'h7;
      instr_code = 'h2;
    end
    18'b000000010001110011: // EBREAK
    begin
      instr_type = 'h7;
      instr_code = 'h3;
    end
    18'b????????0011110011: // CSRRW
    begin
      instr_type = 'h8;
      instr_code = 'h0;
    end
    18'b????????0101110011: // CSRRS
    begin
      instr_type = 'h8;
      instr_code = 'h1;
    end
    18'b????????0111110011: // CSRRC
    begin
      instr_type = 'h8;
      instr_code = 'h2;
    end
    18'b????????1011110011: // CSRRWI
    begin
      instr_type = 'h8;
      instr_code = 'h3;
    end
    18'b????????1101110011: // CSRRSI
    begin
      instr_type = 'h8;
      instr_code = 'h4;
    end
    18'b????????1111110011: // CSRRCI
    begin
      instr_type = 'h8;
      instr_code = 'h0;
    end
    default: 
    begin
      instr_type = 'h0;
      instr_code = 'h0;
    end
  endcase
  decode = {instr_type, instr_code};
end

endmodule

rtl/cpu/pc_gen.sv



module pc_gen
(
  // Global interface
  input logic clk,
  input logic rst_n,

  // Ifetch interface
  input logic[xlen-1:0] instruction,
  output logic ok_o,

  // Register interface
  output logic[32:0] data,
  input logic ok_i,

  // PC control interface
  output logic[xlen-1:0] pc
  );

// PARAMETERS

parameter xlen = 32;

// local variables

logic[7:0] decode;

logic[17:0] decode_parse_instr;
logic[24:0] reg_imm_parse_instr;

logic[32:0] data_i;

logic[xlen-1:0] start_address = 'h0;
logic[xlen-1:0] pc_next;

// Decode

always begin
  decode_parse_instr = {instruction[31:25], instruction[20], instruction[14:12], instruction[6:0]};
  reg_imm_parse_instr = instruction[31:7];
end

decoder_PG decoder
(
  .instruction(decode_parse_instr),
  .decode(decode)
);

// calc new address
initial begin
  pc = start_address;
end

always begin
  if(rst_n)begin
    if (decode == 'h7) begin
      pc_next = pc + {11'h0 , instruction[20], instruction[10:1], instruction[11], instruction[19:12]};
    end else begin
      pc_next = pc + 4;
    end
  end
end
always @(posedge clk) begin
  if(rst_n)begin
    pc <= pc_next;
  end
end


always begin
  data_i = {decode, reg_imm_parse_instr};
end

fifo #(.DATA_SIZE($bits(data_i))) pipeline_d2r
(
  .clk(clk),
  .rst_n(rst_n),
  .data_i(data_i),
  .valide(1),
  .data_o(data),
  .ok(ok_i)
);

always begin
  ok_o = 1;
end

endmodule

rtl/cpu/ifetch.sv




module ifetch
//import CPU_config::*;
(
	// Global interface
	input logic clk,
	input logic rst_n,

  // Memory interface
  output logic[xlen-1:0] target_address,
  input logic[xlen-1:0] resp,

	// Pc_gen interface
	output logic[xlen-1:0] data,
  input logic ok,

  // PC Control interface
  input logic[xlen-1:0] target
);
parameter xlen = 32;


always begin
  target_address = target;
end


fifo #(.DATA_SIZE(xlen)) pipeline_f2d
(
  .clk(clk),
  .rst_n(rst_n),
  .data_i(resp),
  .valide(1),
  .data_o(data),
  .ok(ok)
);

endmodule

rtl/cpu/cpu.sv



module cpu
//import CPU_config::*;
(
  // Global inputs
  input logic clk,
  input logic rst_n,

  
  // system inputs
  input logic [xlen-1:0] resp_data,

  // system outputs
  output logic [xlen-1:0] adr

);
  // PARAMETERS
  parameter xlen = 32;
  
  // local variables

  // ifetch
  logic[xlen-1:0] data_f2d;

  // pc_gen
  logic ok_d2f;
  logic[32:0] data_d2r;
  logic ok_r2p;

  // PC control 
  logic[xlen-1:0] target;

  // instruction fetch Unit
  ifetch ifetch
  (
    .clk(clk),
    .rst_n(rst_n),
    .target_address(adr),
    .resp(resp_data),
    .data(data_f2d),
    .ok(ok_d2f),
    .target(target)
  );

  pc_gen pc_gen
  (
    .clk(clk),
    .rst_n(rst_n),
    .instruction(data_f2d),
    .ok_o(ok_d2f),
    .data(data_d2r),
    .ok_i(ok_r2p),
    .pc(target)
  );

  register_manager register_manager
  (
    .clk(clk),
    .rst_n(rst_n),
    .data(data_d2r),
    .ok_o(ok_r2p)
  );

endmodule

build/sim/tb_cpu.sv





module tb_cpu
//import system_config::*;
(
  input logic clk,
  input logic rst_n
);
  parameter xlen = 32;
  // Debug
  //logic [32:0] counter;


  logic [xlen-1:0] adr;
  logic [xlen-1:0] resp_data = 32'h0;
  // MODULES:

  // CPU
  cpu cpu 
  (
    clk,
    rst_n,
    resp_data,
    adr
  );

  // memory
  basic_mem mem
  (
    clk,
    rst_n,
    adr,
    resp_data
  );
  integer i;
  integer j;
  initial begin
    $display("Loading memory.");
    
    $readmemh("../../software/tests/ihex", mem.data);      
    $displayh(mem.data);
  end


endmodule

build/sim/waveform.vcd
$version Generated by VerilatedVcd $end
$date Sun May  7 18:56:12 2023
 $end
$timescale   1ps $end

 $scope module TOP $end
  $var wire  1 . clk $end
  $var wire  1 / rst_n $end
  $scope module tb_cpu $end
   $var wire 32 # adr [31:0] $end
   $var wire  1 . clk $end
   $var wire 32 3 i [31:0] $end
   $var wire 32 4 j [31:0] $end
   $var wire 32 0 resp_data [31:0] $end
   $var wire  1 / rst_n $end
   $var wire 32 2 xlen [31:0] $end
   $scope module cpu $end
    $var wire 32 # adr [31:0] $end
    $var wire  1 . clk $end
    $var wire 33 % data_d2r [32:0] $end
    $var wire 32 $ data_f2d [31:0] $end
    $var wire  1 5 ok_d2f $end
    $var wire  1 5 ok_r2p $end
    $var wire 32 0 resp_data [31:0] $end
    $var wire  1 / rst_n $end
    $var wire 32 # target [31:0] $end
    $var wire 32 2 xlen [31:0] $end
    $scope module ifetch $end
     $var wire  1 . clk $end
     $var wire 32 $ data [31:0] $end
     $var wire  1 5 ok $end
     $var wire 32 0 resp [31:0] $end
     $var wire  1 / rst_n $end
     $var wire 32 # target [31:0] $end
     $var wire 32 # target_address [31:0] $end
     $var wire 32 2 xlen [31:0] $end
     $scope module pipeline_f2d $end
      $var wire 32 2 DATA_SIZE [31:0] $end
      $var wire  1 . clk $end
      $var wire 32 0 data [31:0] $end
      $var wire 32 0 data_i [31:0] $end
      $var wire 32 $ data_o [31:0] $end
      $var wire  1 5 ok $end
      $var wire  1 / rst_n $end
      $var wire  1 5 valide $end
     $upscope $end
    $upscope $end
    $scope module pc_gen $end
     $var wire  1 . clk $end
     $var wire 33 % data [32:0] $end
     $var wire 33 * data_i [32:0] $end
     $var wire  8 ' decode [7:0] $end
     $var wire 18 ( decode_parse_instr [17:0] $end
     $var wire 32 $ instruction [31:0] $end
     $var wire  1 5 ok_i $end
     $var wire  1 5 ok_o $end
     $var wire 32 # pc [31:0] $end
     $var wire 32 1 pc_next [31:0] $end
     $var wire 25 ) reg_imm_parse_instr [24:0] $end
     $var wire  1 / rst_n $end
     $var wire 32 6 start_address [31:0] $end
     $var wire 32 2 xlen [31:0] $end
     $scope module decoder $end
      $var wire  8 ' decode [7:0] $end
      $var wire  4 - instr_code [3:0] $end
      $var wire  4 , instr_type [3:0] $end
      $var wire 18 ( instruction [17:0] $end
      $var wire 32 2 xlen [31:0] $end
     $upscope $end
     $scope module pipeline_d2r $end
      $var wire 32 7 DATA_SIZE [31:0] $end
      $var wire  1 . clk $end
      $var wire 33 * data [32:0] $end
      $var wire 33 * data_i [32:0] $end
      $var wire 33 % data_o [32:0] $end
      $var wire  1 5 ok $end
      $var wire  1 / rst_n $end
      $var wire  1 5 valide $end
     $upscope $end
    $upscope $end
    $scope module register_manager $end
     $var wire  1 . clk $end
     $var wire 33 % data [32:0] $end
     $var wire  1 5 ok_o $end
     $var wire  1 / rst_n $end
    $upscope $end
   $upscope $end
   $scope module mem $end
    $var wire 32 8 CELL_SIZE [31:0] $end
    $var wire 32 9 NB_CELLS [31:0] $end
    $var wire 32 # adr [31:0] $end
    $var wire  1 . clk $end
    $var wire 32 0 resp_data [31:0] $end
    $var wire  1 / rst_n $end
    $var wire 32 2 xlen [31:0] $end
   $upscope $end
  $upscope $end
 $upscope $end
$enddefinitions $end


#0
b00000000000000000000000000000000 #
b00000000000000000000000000000000 $
b000000000000000000000000000000000 %
b00000000 '
b000000000000000000 (
b0000000000000000000000000 )
b000000000000000000000000000000000 *
b0000 ,
b0000 -
1.
0/
b00000000000000000000000000000000 0
b00000000000000000000000000000000 1
b00000000000000000000000000100000 2
b00000000000000000000000000000000 3
b00000000000000000000000000000000 4
15
b00000000000000000000000000000000 6
b00000000000000000000000000100001 7
b00000000000000000000000000001000 8
b00000000000000000000010000000000 9
#1
0.
#2
1.
#3
0.
#4
1.
#5
0.
#6
1.
#7
0.
#8
1.
#9
0.
#10
1.
#11
0.
#12
1.
#13
0.
#14
1.
#15
0.
#16
1.
#17
0.
#18
1.
#19
0.
#20
1.
#21
0.
#22
1.
#23
0.
#24
1.
#25
0.
#26
1.
#27
0.
#28
1.
#29
0.
#30
1.
#31
0.
#32
1.
#33
0.
#34
1.
#35
0.
#36
1.
#37
0.
#38
1.
#39
0.
#40
1.
#41
0.
#42
1.
#43
0.
#44
1.
#45
0.
#46
1.
#47
0.
#48
1.
#49
0.
#50
1.
#51
0.
#52
1.
#53
0.
#54
1.
#55
0.
#56
1.
#57
0.
#58
1.
#59
0.
#60
1.
#61
0.
#62
1.
#63
0.
#64
1.
#65
0.
#66
1.
#67
0.
#68
1.
#69
0.
#70
1.
#71
0.
#72
1.
#73
0.
#74
1.
#75
0.
#76
1.
#77
0.
#78
1.
#79
0.
#80
1.
#81
0.
#82
1.
#83
0.
#84
1.
#85
0.
#86
1.
#87
0.
#88
1.
#89
0.
#90
1.
#91
0.
#92
1.
#93
0.
#94
1.
#95
0.
#96
1.
#97
0.
#98
1.
#99
0.
#100
1.
1/
b00000000000000000000000000000100 1
#101
0.
b11111110000000010000000100010011 0
#102
b00000000000000000000000000000100 #
b11111110000000010000000100010011 $
b00100101 '
b111111100000010011 (
b1111111000000001000000010 )
b001001011111111000000001000000010 *
b0010 ,
b0101 -
1.
b00000000000000000000000000001000 1
#103
0.
b00000000100000010010111000100011 0
#104
b00000000000000000000000000001000 #
b00000000100000010010111000100011 $
b001001011111111000000001000000010 %
b00110010 '
b000000000100100011 (
b0000000010000001001011100 )
b001100100000000010000001001011100 *
b0011 ,
b0010 -
1.
b00000000000000000000000000001100 1
#105
0.
b00000010000000010000010000010011 0
#106
b00000000000000000000000000001100 #
b00000010000000010000010000010011 $
b001100100000000010000001001011100 %
b00100101 '
b000000100000010011 (
b0000001000000001000001000 )
b001001010000001000000001000001000 *
b0010 ,
b0101 -
1.
b00000000000000000000000000010000 1
#107
0.
b00000000000100000000011110010011 0
#108
b00000000000000000000000000010000 #
b00000000000100000000011110010011 $
b001001010000001000000001000001000 %
b000000010000010011 (
b0000000000010000000001111 )
b001001010000000000010000000001111 *
1.
b00000000000000000000000000010100 1
#109
0.
b11111110111101000010011000100011 0
#110
b00000000000000000000000000010100 #
b11111110111101000010011000100011 $
b001001010000000000010000000001111 %
b00110010 '
b111111110100100011 (
b1111111011110100001001100 )
b001100101111111011110100001001100 *
b0011 ,
b0010 -
1.
b00000000000000000000000000011000 1
#111
0.
b00000000001000000000011110010011 0
#112
b00000000000000000000000000011000 #
b00000000001000000000011110010011 $
b001100101111111011110100001001100 %
b00100101 '
b000000000000010011 (
b0000000000100000000001111 )
b001001010000000000100000000001111 *
b0010 ,
b0101 -
1.
b00000000000000000000000000011100 1
#113
0.
b11111110111101000010010000100011 0
#114
b00000000000000000000000000011100 #
b11111110111101000010010000100011 $
b001001010000000000100000000001111 %
b00110010 '
b111111110100100011 (
b1111111011110100001001000 )
b001100101111111011110100001001000 *
b0011 ,
b0010 -
1.
b00000000000000000000000000100000 1
#115
0.
b11111110110001000010011100000011 0
#116
b00000000000000000000000000100000 #
b11111110110001000010011100000011 $
b001100101111111011110100001001000 %
b00100011 '
b111111100100000011 (
b1111111011000100001001110 )
b001000111111111011000100001001110 *
b0010 ,
b0011 -
1.
b00000000000000000000000000100100 1
#117
0.
b11111110100001000010011110000011 0
#118
b00000000000000000000000000100100 #
b11111110100001000010011110000011 $
b001000111111111011000100001001110 %
b1111111010000100001001111 )
b001000111111111010000100001001111 *
1.
b00000000000000000000000000101000 1
#119
0.
b00000000111101110000011110110011 0
#120
b00000000000000000000000000101000 #
b00000000111101110000011110110011 $
b001000111111111010000100001001111 %
b00010011 '
b000000010000110011 (
b0000000011110111000001111 )
b000100110000000011110111000001111 *
b0001 ,
1.
b00000000000000000000000000101100 1
#121
0.
b11111110111101000010001000100011 0
#122
b00000000000000000000000000101100 #
b11111110111101000010001000100011 $
b000100110000000011110111000001111 %
b00110010 '
b111111110100100011 (
b1111111011110100001000100 )
b001100101111111011110100001000100 *
b0011 ,
b0010 -
1.
b00000000000000000000000000110000 1
#123
0.
b11111110010001000010011110000011 0
#124
b00000000000000000000000000110000 #
b11111110010001000010011110000011 $
b001100101111111011110100001000100 %
b00100011 '
b111111100100000011 (
b1111111001000100001001111 )
b001000111111111001000100001001111 *
b0010 ,
b0011 -
1.
b00000000000000000000000000110100 1
#125
0.
b11111111110101111000011110010011 0
#126
b00000000000000000000000000110100 #
b11111111110101111000011110010011 $
b001000111111111001000100001001111 %
b00100101 '
b111111110000010011 (
b1111111111010111100001111 )
b001001011111111111010111100001111 *
b0101 -
1.
b00000000000000000000000000111000 1
#127
0.
b00000000000101111011011110010011 0
#128
b00000000000000000000000000111000 #
b00000000000101111011011110010011 $
b001001011111111111010111100001111 %
b00100111 '
b000000010110010011 (
b0000000000010111101101111 )
b001001110000000000010111101101111 *
b0111 -
1.
b00000000000000000000000000111100 1
#129
0.
b00001111111101111111011110010011 0
#130
b00000000000000000000000000111100 #
b00001111111101111111011110010011 $
b001001110000000000010111101101111 %
b00101010 '
b000011111110010011 (
b0000111111110111111101111 )
b001010100000111111110111111101111 *
b1010 -
1.
b00000000000000000000000001000000 1
#131
0.
b00000000000001111000010100010011 0
#132
b00000000000000000000000001000000 #
b00000000000001111000010100010011 $
b001010100000111111110111111101111 %
b00100101 '
b000000000000010011 (
b0000000000000111100001010 )
b001001010000000000000111100001010 *
b0101 -
1.
b00000000000000000000000001000100 1
#133
0.
b00000001110000010010010000000011 0
#134
b00000000000000000000000001000100 #
b00000001110000010010010000000011 $
b001001010000000000000111100001010 %
b00100011 '
b000000000100000011 (
b0000000111000001001001000 )
b001000110000000111000001001001000 *
b0011 -
1.
b00000000000000000000000001001000 1
#135
0.
b00000010000000010000000100010011 0
#136
b00000000000000000000000001001000 #
b00000010000000010000000100010011 $
b001000110000000111000001001001000 %
b00100101 '
b000000100000010011 (
b0000001000000001000000010 )
b001001010000001000000001000000010 *
b0101 -
1.
b00000000000000000000000001001100 1
#137
0.
b00000000000000001000000001100111 0
#138
b00000000000000000000000001001100 #
b00000000000000001000000001100111 $
b001001010000001000000001000000010 %
b00100000 '
b000000000001100111 (
b0000000000000000100000000 )
b001000000000000000000000100000000 *
b0000 -
1.
b00000000000000000000000001010000 1
#139
0.
b00000000000000000000000000000000 0
#140
b00000000000000000000000001010000 #
b00000000000000000000000000000000 $
b001000000000000000000000100000000 %
b00000000 '
b000000000000000000 (
b0000000000000000000000000 )
b000000000000000000000000000000000 *
b0000 ,
1.
b00000000000000000000000001010100 1
#141
0.
#142
b00000000000000000000000001010100 #
b000000000000000000000000000000000 %
1.
b00000000000000000000000001011000 1
#143
0.
#144
b00000000000000000000000001011000 #
1.
b00000000000000000000000001011100 1
#145
0.
#146
b00000000000000000000000001011100 #
1.
b00000000000000000000000001100000 1
#147
0.
#148
b00000000000000000000000001100000 #
1.
b00000000000000000000000001100100 1
#149
0.
#150
b00000000000000000000000001100100 #
1.
b00000000000000000000000001101000 1
#151
0.
#152
b00000000000000000000000001101000 #
1.
b00000000000000000000000001101100 1
#153
0.
#154
b00000000000000000000000001101100 #
1.
b00000000000000000000000001110000 1
#155
0.
#156
b00000000000000000000000001110000 #
1.
b00000000000000000000000001110100 1
#157
0.
#158
b00000000000000000000000001110100 #
1.
b00000000000000000000000001111000 1
#159
0.
#160
b00000000000000000000000001111000 #
1.
b00000000000000000000000001111100 1
#161
0.
#162
b00000000000000000000000001111100 #
1.
b00000000000000000000000010000000 1
#163
0.
#164
b00000000000000000000000010000000 #
1.
b00000000000000000000000010000100 1
#165
0.
#166
b00000000000000000000000010000100 #
1.
b00000000000000000000000010001000 1
#167
0.
#168
b00000000000000000000000010001000 #
1.
b00000000000000000000000010001100 1
#169
0.
#170
b00000000000000000000000010001100 #
1.
b00000000000000000000000010010000 1
#171
0.
#172
b00000000000000000000000010010000 #
1.
b00000000000000000000000010010100 1
#173
0.
#174
b00000000000000000000000010010100 #
1.
b00000000000000000000000010011000 1
#175
0.
#176
b00000000000000000000000010011000 #
1.
b00000000000000000000000010011100 1
#177
0.
#178
b00000000000000000000000010011100 #
1.
b00000000000000000000000010100000 1
#179
0.
#180
b00000000000000000000000010100000 #
1.
b00000000000000000000000010100100 1
#181
0.
#182
b00000000000000000000000010100100 #
1.
b00000000000000000000000010101000 1
#183
0.
#184
b00000000000000000000000010101000 #
1.
b00000000000000000000000010101100 1
#185
0.
#186
b00000000000000000000000010101100 #
1.
b00000000000000000000000010110000 1
#187
0.
#188
b00000000000000000000000010110000 #
1.
b00000000000000000000000010110100 1
#189
0.
#190
b00000000000000000000000010110100 #
1.
b00000000000000000000000010111000 1
#191
0.
#192
b00000000000000000000000010111000 #
1.
b00000000000000000000000010111100 1
#193
0.
#194
b00000000000000000000000010111100 #
1.
b00000000000000000000000011000000 1
#195
0.
#196
b00000000000000000000000011000000 #
1.
b00000000000000000000000011000100 1
#197
0.
#198
b00000000000000000000000011000100 #
1.
b00000000000000000000000011001000 1
#199
0.
#200
b00000000000000000000000011001000 #
1.
b00000000000000000000000011001100 1
#201
0.
#202
b00000000000000000000000011001100 #
1.
b00000000000000000000000011010000 1
#203
0.
#204
b00000000000000000000000011010000 #
1.
b00000000000000000000000011010100 1
#205
0.
#206
b00000000000000000000000011010100 #
1.
b00000000000000000000000011011000 1
#207
0.
#208
b00000000000000000000000011011000 #
1.
b00000000000000000000000011011100 1
#209
0.
#210
b00000000000000000000000011011100 #
1.
b00000000000000000000000011100000 1
#211
0.
#212
b00000000000000000000000011100000 #
1.
b00000000000000000000000011100100 1
#213
0.
#214
b00000000000000000000000011100100 #
1.
b00000000000000000000000011101000 1
#215
0.
#216
b00000000000000000000000011101000 #
1.
b00000000000000000000000011101100 1
#217
0.
#218
b00000000000000000000000011101100 #
1.
b00000000000000000000000011110000 1
#219
0.
#220
b00000000000000000000000011110000 #
1.
b00000000000000000000000011110100 1
#221
0.
#222
b00000000000000000000000011110100 #
1.
b00000000000000000000000011111000 1
#223
0.
#224
b00000000000000000000000011111000 #
1.
b00000000000000000000000011111100 1
#225
0.
#226
b00000000000000000000000011111100 #
1.
b00000000000000000000000100000000 1
#227
0.
#228
b00000000000000000000000100000000 #
1.
b00000000000000000000000100000100 1
#229
0.
#230
b00000000000000000000000100000100 #
1.
b00000000000000000000000100001000 1
#231
0.
#232
b00000000000000000000000100001000 #
1.
b00000000000000000000000100001100 1
#233
0.
#234
b00000000000000000000000100001100 #
1.
b00000000000000000000000100010000 1
#235
0.
#236
b00000000000000000000000100010000 #
1.
b00000000000000000000000100010100 1
#237
0.
#238
b00000000000000000000000100010100 #
1.
b00000000000000000000000100011000 1
#239
0.
#240
b00000000000000000000000100011000 #
1.
b00000000000000000000000100011100 1
#241
0.
#242
b00000000000000000000000100011100 #
1.
b00000000000000000000000100100000 1
#243
0.
#244
b00000000000000000000000100100000 #
1.
b00000000000000000000000100100100 1
#245
0.
#246
b00000000000000000000000100100100 #
1.
b00000000000000000000000100101000 1
#247
0.
#248
b00000000000000000000000100101000 #
1.
b00000000000000000000000100101100 1
#249
0.
#250
b00000000000000000000000100101100 #
1.
b00000000000000000000000100110000 1
#251
0.
#252
b00000000000000000000000100110000 #
1.
b00000000000000000000000100110100 1
#253
0.
#254
b00000000000000000000000100110100 #
1.
b00000000000000000000000100111000 1
#255
0.
#256
b00000000000000000000000100111000 #
1.
b00000000000000000000000100111100 1
#257
0.
#258
b00000000000000000000000100111100 #
1.
b00000000000000000000000101000000 1
#259
0.
#260
b00000000000000000000000101000000 #
1.
b00000000000000000000000101000100 1
#261
0.
#262
b00000000000000000000000101000100 #
1.
b00000000000000000000000101001000 1
#263
0.
#264
b00000000000000000000000101001000 #
1.
b00000000000000000000000101001100 1
#265
0.
#266
b00000000000000000000000101001100 #
1.
b00000000000000000000000101010000 1
#267
0.
#268
b00000000000000000000000101010000 #
1.
b00000000000000000000000101010100 1
#269
0.
#270
b00000000000000000000000101010100 #
1.
b00000000000000000000000101011000 1
#271
0.
#272
b00000000000000000000000101011000 #
1.
b00000000000000000000000101011100 1
#273
0.
#274
b00000000000000000000000101011100 #
1.
b00000000000000000000000101100000 1
#275
0.
#276
b00000000000000000000000101100000 #
1.
b00000000000000000000000101100100 1
#277
0.
#278
b00000000000000000000000101100100 #
1.
b00000000000000000000000101101000 1
#279
0.
#280
b00000000000000000000000101101000 #
1.
b00000000000000000000000101101100 1
#281
0.
#282
b00000000000000000000000101101100 #
1.
b00000000000000000000000101110000 1
#283
0.
#284
b00000000000000000000000101110000 #
1.
b00000000000000000000000101110100 1
#285
0.
#286
b00000000000000000000000101110100 #
1.
b00000000000000000000000101111000 1
#287
0.
#288
b00000000000000000000000101111000 #
1.
b00000000000000000000000101111100 1
#289
0.
#290
b00000000000000000000000101111100 #
1.
b00000000000000000000000110000000 1
#291
0.
#292
b00000000000000000000000110000000 #
1.
b00000000000000000000000110000100 1
#293
0.
#294
b00000000000000000000000110000100 #
1.
b00000000000000000000000110001000 1
#295
0.
#296
b00000000000000000000000110001000 #
1.
b00000000000000000000000110001100 1
#297
0.
#298
b00000000000000000000000110001100 #
1.
b00000000000000000000000110010000 1
#299
0.
#300
b00000000000000000000000110010000 #
1.
b00000000000000000000000110010100 1
#301
0.
#302
b00000000000000000000000110010100 #
1.
b00000000000000000000000110011000 1
#303
0.
#304
b00000000000000000000000110011000 #
1.
b00000000000000000000000110011100 1
#305
0.
#306
b00000000000000000000000110011100 #
1.
b00000000000000000000000110100000 1
#307
0.
#308
b00000000000000000000000110100000 #
1.
b00000000000000000000000110100100 1
#309
0.
#310
b00000000000000000000000110100100 #
1.
b00000000000000000000000110101000 1
#311
0.
#312
b00000000000000000000000110101000 #
1.
b00000000000000000000000110101100 1
#313
0.
#314
b00000000000000000000000110101100 #
1.
b00000000000000000000000110110000 1
#315
0.
#316
b00000000000000000000000110110000 #
1.
b00000000000000000000000110110100 1
#317
0.
#318
b00000000000000000000000110110100 #
1.
b00000000000000000000000110111000 1
#319
0.
#320
b00000000000000000000000110111000 #
1.
b00000000000000000000000110111100 1
#321
0.
#322
b00000000000000000000000110111100 #
1.
b00000000000000000000000111000000 1
#323
0.
#324
b00000000000000000000000111000000 #
1.
b00000000000000000000000111000100 1
#325
0.
#326
b00000000000000000000000111000100 #
1.
b00000000000000000000000111001000 1
#327
0.
#328
b00000000000000000000000111001000 #
1.
b00000000000000000000000111001100 1
#329
0.
#330
b00000000000000000000000111001100 #
1.
b00000000000000000000000111010000 1
#331
0.
#332
b00000000000000000000000111010000 #
1.
b00000000000000000000000111010100 1
#333
0.
#334
b00000000000000000000000111010100 #
1.
b00000000000000000000000111011000 1
#335
0.
#336
b00000000000000000000000111011000 #
1.
b00000000000000000000000111011100 1
#337
0.
#338
b00000000000000000000000111011100 #
1.
b00000000000000000000000111100000 1
#339
0.
#340
b00000000000000000000000111100000 #
1.
b00000000000000000000000111100100 1
#341
0.
#342
b00000000000000000000000111100100 #
1.
b00000000000000000000000111101000 1
#343
0.
#344
b00000000000000000000000111101000 #
1.
b00000000000000000000000111101100 1
#345
0.
#346
b00000000000000000000000111101100 #
1.
b00000000000000000000000111110000 1
#347
0.
#348
b00000000000000000000000111110000 #
1.
b00000000000000000000000111110100 1
#349
0.
#350
b00000000000000000000000111110100 #
1.
b00000000000000000000000111111000 1
#351
0.
#352
b00000000000000000000000111111000 #
1.
b00000000000000000000000111111100 1
#353
0.
#354
b00000000000000000000000111111100 #
1.
b00000000000000000000001000000000 1
#355
0.
#356
b00000000000000000000001000000000 #
1.
b00000000000000000000001000000100 1
#357
0.
#358
b00000000000000000000001000000100 #
1.
b00000000000000000000001000001000 1
#359
0.
#360
b00000000000000000000001000001000 #
1.
b00000000000000000000001000001100 1
#361
0.
#362
b00000000000000000000001000001100 #
1.
b00000000000000000000001000010000 1
#363
0.
#364
b00000000000000000000001000010000 #
1.
b00000000000000000000001000010100 1
#365
0.
#366
b00000000000000000000001000010100 #
1.
b00000000000000000000001000011000 1
#367
0.
#368
b00000000000000000000001000011000 #
1.
b00000000000000000000001000011100 1
#369
0.
#370
b00000000000000000000001000011100 #
1.
b00000000000000000000001000100000 1
#371
0.
